{"_invocation_id": "ff5c0a3f-b31e-4a46-9127-30632e88c560", "linked": {"0": {"name": "source.financas_data_pipeline.bronze.ativos", "type": "source", "succ": [7]}, "1": {"name": "source.financas_data_pipeline.bronze.indicadores", "type": "source", "succ": [8]}, "2": {"name": "source.financas_data_pipeline.bronze.tesouro", "type": "source", "succ": [9]}, "3": {"name": "source.financas_data_pipeline.prata.ativos", "type": "source"}, "4": {"name": "source.financas_data_pipeline.prata.indicadores", "type": "source"}, "5": {"name": "source.financas_data_pipeline.prata.tesouro", "type": "source"}, "6": {"name": "model.financas_data_pipeline.produto_dados_financeiros", "type": "model"}, "7": {"name": "model.financas_data_pipeline.ativos", "type": "model", "succ": [6]}, "8": {"name": "model.financas_data_pipeline.indicadores", "type": "model", "succ": [6]}, "9": {"name": "model.financas_data_pipeline.tesouro", "type": "model", "succ": [6]}}}